ra2mix/__init__.py
ra2mix/cccrypto.py
ra2mix/checksum.py
ra2mix/const.py
ra2mix/reader.py
ra2mix/writer.py
ra2mix/data/global_mix_database.json
ra2mix-1.0.3.dist-info/LICENSE
ra2mix-1.0.3.dist-info/METADATA
ra2mix-1.0.3.dist-info/WHEEL
ra2mix-1.0.3.dist-info/top_level.txt
ra2mix-1.0.3.dist-info/RECORD
