Metadata-Version: 2.1
Name: ra2mix
Version: 1.0.3
Summary: ra2mix is a python library for working with Red Alert 2 / Yuri's Revenge *.mix files
Author-email: nyte_owl <nyteowldev@gmail.com>
Project-URL: Homepage, https://github.com/endless-creation/ra2mix
Classifier: Programming Language :: Python :: 3.11
Classifier: License :: OSI Approved :: GNU General Public License v3 (GPLv3)
Classifier: Operating System :: OS Independent
Requires-Python: >=3.11
License-File: LICENSE
Requires-Dist: blowfish ==0.6.1
